msh/__init__.py
msh/catalog.py
msh/constants.py
msh/dependency.py
msh/git_utils.py
msh/logger.py
msh/main.py
msh/orchestrator.py
msh/ai/__init__.py
msh/ai/ast_generator.py
msh/ai/config.py
msh/ai/context_pack.py
msh/ai/diff.py
msh/ai/manifest.py
msh/ai/metadata.py
msh/ai/metadata_cache.py
msh/ai/patch.py
msh/ai/prompts.py
msh/ai/providers.py
msh/ai/safety.py
msh/ai/tools.py
msh/ai/commands/__init__.py
msh/ai/commands/explain.py
msh/ai/commands/fix.py
msh/ai/commands/new.py
msh/ai/commands/review.py
msh/ai/commands/tests.py
msh/ai/tools/__init__.py
msh/commands/__init__.py
msh/commands/ai.py
msh/commands/asset.py
msh/commands/config.py
msh/commands/create.py
msh/commands/discover.py
msh/commands/doctor.py
msh/commands/fmt.py
msh/commands/glossary.py
msh/commands/init.py
msh/commands/inspect.py
msh/commands/manifest.py
msh/commands/plan.py
msh/commands/publish.py
msh/commands/run.py
msh/commands/sample.py
msh/commands/state.py
msh/commands/ui.py
msh/commands/validate.py
msh/compiler/__init__.py
msh/compiler/artifacts.py
msh/compiler/dbt_generator.py
msh/compiler/macros.py
msh/compiler/model.py
msh/compiler/parser.py
msh/glossary/__init__.py
msh/glossary/glossary.py
msh/managers/__init__.py
msh/managers/ingest.py
msh/managers/transform.py
msh/ui_static/App.jsx
msh/ui_static/app.js
msh/ui_static/index.html
msh/ui_static/main.js
msh/ui_static/.msh/ui/index.html
msh/utils/__init__.py
msh/utils/config.py
msh_cli-0.1.1.dist-info/licenses/LICENSE.txt
msh_cli-0.1.1.dist-info/METADATA
msh_cli-0.1.1.dist-info/WHEEL
msh_cli-0.1.1.dist-info/entry_points.txt
msh_cli-0.1.1.dist-info/top_level.txt
msh_cli-0.1.1.dist-info/RECORD
