Metadata-Version: 2.4
Name: msh-cli
Version: 0.1.1
Summary: The Command Line Interface for the msh atomic data platform.
Author-email: Januka Peiris <jaypeiris91@gmail.com>
License: Business Source License 1.1 (BSL 1.1)
Requires-Python: >=3.11
License-File: LICENSE.txt
Requires-Dist: click
Requires-Dist: pyyaml
Requires-Dist: msh-engine>=0.1.1
Requires-Dist: rich
Provides-Extra: polyglot
Requires-Dist: polars; extra == "polyglot"
Requires-Dist: pandas; extra == "polyglot"
Dynamic: license-file
